{
  "source_application_id": "HO-IF-2026-0000982",
  "source_reference": "GV-DEMO-0000982",
  "source_channel": "govdirect",
  "visa_type": "innovator-founder",
  "country_code": "GB",
  "submitted_at": "2026-06-07T13:34:00Z",
  "caseworker_id": null,
  "applicant": {
    "email": "lerato.khumalo.2366@yahoo.com",
    "first_name": "Lerato",
    "middle_name": null,
    "last_name": "Khumalo",
    "date_of_birth": "1990-12-16",
    "nationality_code": "ZA",
    "gender": "F"
  },
  "passport_data": {
    "number": "M5752163",
    "issuing_country": "ZA",
    "nationality": "ZA",
    "full_name": "KHUMALO LERATO",
    "date_of_birth": "1990-12-16",
    "gender": "F",
    "issue_date": "2020-12-09",
    "expiry_date": "2030-12-09",
    "mrz_line1": "P<ZAFKHUMALO<<LERATO<<<<<<<<<<<<<<<<<<<<<<<<",
    "mrz_line2": "M5752163<9ZAF9012167F3012095<<<<<<<<<<<<<<06"
  },
  "biometric_verification": {
    "method": "vac_in_person",
    "vac_location": "VAC Manchester - 1 First Street, M15 4FN",
    "vac_appointment_date": "2026-06-13",
    "fingerprints_captured": true,
    "photograph_captured": true,
    "identity_verified_by": "HO-BIO-Officer-3366",
    "verified_at": "2026-06-13T11:15:00Z",
    "provider": "home_office_vac",
    "mrz_check_passed": true,
    "face_match_score": null,
    "liveness_passed": null
  },
  "answers": {
    "personalInfo": {
      "firstName": "Lerato",
      "middleName": null,
      "lastName": "Khumalo",
      "dateOfBirth": "1990-12-16",
      "nationality": "ZA",
      "maritalStatus": "single"
    },
    "employment": {
      "status": "innovator_founder_applicant",
      "employerName": "Endorsed founder venture",
      "sponsorLicenceNumber": null,
      "sponsorStatus": null,
      "sponsorRating": null,
      "jobTitle": "Founder and Chief Executive",
      "annualIncome": 0.0,
      "monthlyGrossPay": 0.0,
      "cosReferenceNumber": null,
      "cosIssueDate": null,
      "cosExpiryDate": null,
      "socCode": null,
      "socTitle": null,
      "socGoingRateAnnual": null,
      "startDate": "2026-08-01",
      "salaryFrequency": null,
      "hoursPerWeek": null,
      "isNewEntrant": null,
      "newEntrantReason": null,
      "previousUkEmployment": false,
      "endorsingBody": "Innovator International",
      "endorsementReference": "IF-END-2026-774901",
      "businessSector": "Climate analytics SaaS"
    },
    "fees": {
      "ihsReferenceNumber": "IHS-2026-2366-0222",
      "visaFeeReference": "VF-2026-IF-000982",
      "paymentConfirmed": true
    },
    "englishLanguage": {
      "exemptNationality": false,
      "testType": "IELTS_ACADEMIC",
      "testReferenceNumber": "26ZA380978KHU",
      "overallScore": 6.5,
      "speakingScore": 7.0,
      "listeningScore": 6.0,
      "readingScore": 6.0,
      "writingScore": 6.5,
      "testDate": "2026-02-18"
    },
    "travelHistory": {
      "previousUkVisas": [],
      "previousUkRefusals": false,
      "previousDeportations": false,
      "countriesVisitedLast5Years": [
        "ZA",
        "GB"
      ]
    },
    "criminalRecord": {
      "hasConvictions": false,
      "hasPendingCharges": false,
      "hasCivilJudgments": false
    },
    "healthDeclaration": {
      "hasTbCertificate": true,
      "hasHealthConditions": false,
      "requiresAccessibility": false,
      "tbCertificateClinicName": "IOM Migration Health Assessment Centre, South Africa",
      "tbCertificateClinicCountry": "ZA"
    },
    "routeSpecific": {
      "route": "innovator-founder",
      "phase": "PHASE_2_QUEUE_ONLY",
      "phase_note": "DIS pipeline configured - full deep review live in Phase 2.",
      "display_label": "Innovator Founder"
    }
  },
  "documents": [
    {
      "document_id": "ho-doc-001-0000982",
      "type": "PASSPORT",
      "filename": "PASSPORT_001.pdf",
      "signed_url": "https://gov-doc-store.homeoffice.gov.uk/applications/HO-IF-2026-0000982/PASSPORT/PASSPORT_001.pdf?sig=HMAC_GOV_SIGNATURE_REDACTED&exp=2026-07-15T23:59:59Z",
      "mime_type": "application/pdf",
      "size_bytes": 2454,
      "uploaded_at": "2026-06-07T12:52:00Z",
      "scanned_by": null,
      "scan_location": "Home Office Casework Hub - Liverpool"
    },
    {
      "document_id": "ho-doc-002-0000982",
      "type": "ENDORSEMENT_LETTER",
      "filename": "ENDORSEMENT_LETTER_001.pdf",
      "signed_url": "https://gov-doc-store.homeoffice.gov.uk/applications/HO-IF-2026-0000982/ENDORSEMENT_LETTER/ENDORSEMENT_LETTER_001.pdf?sig=HMAC_GOV_SIGNATURE_REDACTED&exp=2026-07-15T23:59:59Z",
      "mime_type": "application/pdf",
      "size_bytes": 2446,
      "uploaded_at": "2026-06-07T12:55:00Z",
      "scanned_by": null,
      "scan_location": "Home Office Casework Hub - Glasgow"
    },
    {
      "document_id": "ho-doc-003-0000982",
      "type": "BANK_STATEMENT",
      "filename": "BANK_STATEMENT_001.pdf",
      "signed_url": "https://gov-doc-store.homeoffice.gov.uk/applications/HO-IF-2026-0000982/BANK_STATEMENT/BANK_STATEMENT_001.pdf?sig=HMAC_GOV_SIGNATURE_REDACTED&exp=2026-07-15T23:59:59Z",
      "mime_type": "application/pdf",
      "size_bytes": 2801,
      "uploaded_at": "2026-06-07T12:58:00Z",
      "scanned_by": null,
      "scan_location": "Home Office Casework Hub - Sheffield"
    },
    {
      "document_id": "ho-doc-004-0000982",
      "type": "BANK_STATEMENT",
      "filename": "BANK_STATEMENT_002.pdf",
      "signed_url": "https://gov-doc-store.homeoffice.gov.uk/applications/HO-IF-2026-0000982/BANK_STATEMENT/BANK_STATEMENT_002.pdf?sig=HMAC_GOV_SIGNATURE_REDACTED&exp=2026-07-15T23:59:59Z",
      "mime_type": "application/pdf",
      "size_bytes": 2794,
      "uploaded_at": "2026-06-07T13:01:00Z",
      "scanned_by": null,
      "scan_location": "Home Office Casework Hub - Croydon"
    },
    {
      "document_id": "ho-doc-005-0000982",
      "type": "BUSINESS_PLAN",
      "filename": "BUSINESS_PLAN_001.pdf",
      "signed_url": "https://gov-doc-store.homeoffice.gov.uk/applications/HO-IF-2026-0000982/BUSINESS_PLAN/BUSINESS_PLAN_001.pdf?sig=HMAC_GOV_SIGNATURE_REDACTED&exp=2026-07-15T23:59:59Z",
      "mime_type": "application/pdf",
      "size_bytes": 2446,
      "uploaded_at": "2026-06-07T13:04:00Z",
      "scanned_by": null,
      "scan_location": "Home Office Casework Hub - Glasgow"
    },
    {
      "document_id": "ho-doc-006-0000982",
      "type": "PHOTO",
      "filename": "PHOTO_001.jpg",
      "signed_url": "https://gov-doc-store.homeoffice.gov.uk/applications/HO-IF-2026-0000982/PHOTO/PHOTO_001.jpg?sig=HMAC_GOV_SIGNATURE_REDACTED&exp=2026-07-15T23:59:59Z",
      "mime_type": "image/jpeg",
      "size_bytes": 17622,
      "uploaded_at": "2026-06-07T13:07:00Z",
      "scanned_by": null,
      "scan_location": "Home Office Casework Hub - Croydon"
    }
  ],
  "callback_url": "https://casework-api.homeoffice.gov.uk/api/v1/dis-decisions/HO-IF-2026-0000982",
  "anomaly_type": "fail_rules",
  "anomaly_details": [
    "endorsing-body letter missing mandatory viability assessment",
    "business plan lacks evidence of innovation"
  ],
  "recommendation": "RECOMMEND_REJECT"
}
