{
  "source_application_id": "HO-ST-2026-0000494",
  "source_reference": "GV-DEMO-0000494",
  "source_channel": "govdirect",
  "visa_type": "student",
  "country_code": "GB",
  "submitted_at": "2026-06-16T00:38:00Z",
  "caseworker_id": null,
  "applicant": {
    "email": "ayesha.mirza.2214@yahoo.com",
    "first_name": "Ayesha",
    "middle_name": null,
    "last_name": "Mirza",
    "date_of_birth": "1988-06-25",
    "nationality_code": "PK",
    "gender": "F"
  },
  "passport_data": {
    "number": "K7398975",
    "issuing_country": "PK",
    "nationality": "PK",
    "full_name": "MIRZA AYESHA",
    "date_of_birth": "1988-06-25",
    "gender": "F",
    "issue_date": "2021-07-08",
    "expiry_date": "2031-07-08",
    "mrz_line1": "P<PAKMIRZA<<AYESHA<<<<<<<<<<<<<<<<<<<<<<<<<<",
    "mrz_line2": "K7398975<4PAK8806253F3107081<<<<<<<<<<<<<<00"
  },
  "biometric_verification": {
    "method": "vac_in_person",
    "vac_location": "VAC Cardiff - 2 Central Square, CF10 1FS",
    "vac_appointment_date": "2026-06-13",
    "fingerprints_captured": true,
    "photograph_captured": true,
    "identity_verified_by": "HO-BIO-Officer-3214",
    "verified_at": "2026-06-13T11:15:00Z",
    "provider": "home_office_vac",
    "mrz_check_passed": true,
    "face_match_score": null,
    "liveness_passed": null
  },
  "answers": {
    "personalInfo": {
      "firstName": "Ayesha",
      "middleName": null,
      "lastName": "Mirza",
      "dateOfBirth": "1988-06-25",
      "nationality": "PK",
      "maritalStatus": "married"
    },
    "employment": {
      "status": "student_applicant",
      "employerName": "University of Manchester",
      "sponsorLicenceNumber": "STU-2026-4821",
      "sponsorStatus": "ACTIVE",
      "sponsorRating": "A",
      "jobTitle": "MSc Data Science student",
      "annualIncome": 0.0,
      "monthlyGrossPay": 0.0,
      "cosReferenceNumber": null,
      "cosIssueDate": null,
      "cosExpiryDate": null,
      "socCode": null,
      "socTitle": null,
      "socGoingRateAnnual": null,
      "startDate": "2026-09-22",
      "salaryFrequency": null,
      "hoursPerWeek": null,
      "isNewEntrant": null,
      "newEntrantReason": null,
      "previousUkEmployment": false,
      "casReferenceNumber": "CAS-2026-UM-438921",
      "courseTitle": "MSc Data Science",
      "courseLevel": "RQF Level 7",
      "tuitionFeesGbp": 28600,
      "maintenanceFundsGbp": 12006
    },
    "fees": {
      "ihsReferenceNumber": "IHS-2026-2214-7638",
      "visaFeeReference": "VF-2026-ST-000494",
      "paymentConfirmed": true
    },
    "englishLanguage": {
      "exemptNationality": false,
      "testType": "IELTS_ACADEMIC",
      "testReferenceNumber": "26PK635014MIR",
      "overallScore": 7.5,
      "speakingScore": 7.5,
      "listeningScore": 8.0,
      "readingScore": 7.5,
      "writingScore": 7.5,
      "testDate": "2026-02-18"
    },
    "travelHistory": {
      "previousUkVisas": [],
      "previousUkRefusals": false,
      "previousDeportations": false,
      "countriesVisitedLast5Years": [
        "PK",
        "GB"
      ]
    },
    "criminalRecord": {
      "hasConvictions": false,
      "hasPendingCharges": false,
      "hasCivilJudgments": false
    },
    "healthDeclaration": {
      "hasTbCertificate": true,
      "hasHealthConditions": false,
      "requiresAccessibility": false,
      "tbCertificateClinicName": "IOM Migration Health Assessment Centre, Pakistan",
      "tbCertificateClinicCountry": "PK"
    },
    "routeSpecific": {
      "route": "student",
      "phase": "PHASE_2_QUEUE_ONLY",
      "phase_note": "DIS pipeline configured - full deep review live in Phase 2.",
      "display_label": "Student"
    }
  },
  "documents": [
    {
      "document_id": "ho-doc-001-0000494",
      "type": "PASSPORT",
      "filename": "PASSPORT_001.pdf",
      "signed_url": "https://gov-doc-store.homeoffice.gov.uk/applications/HO-ST-2026-0000494/PASSPORT/PASSPORT_001.pdf?sig=HMAC_GOV_SIGNATURE_REDACTED&exp=2026-07-15T23:59:59Z",
      "mime_type": "application/pdf",
      "size_bytes": 2443,
      "uploaded_at": "2026-06-15T23:56:00Z",
      "scanned_by": null,
      "scan_location": "Home Office Casework Hub - Liverpool"
    },
    {
      "document_id": "ho-doc-002-0000494",
      "type": "BANK_STATEMENT",
      "filename": "BANK_STATEMENT_001.pdf",
      "signed_url": "https://gov-doc-store.homeoffice.gov.uk/applications/HO-ST-2026-0000494/BANK_STATEMENT/BANK_STATEMENT_001.pdf?sig=HMAC_GOV_SIGNATURE_REDACTED&exp=2026-07-15T23:59:59Z",
      "mime_type": "application/pdf",
      "size_bytes": 2785,
      "uploaded_at": "2026-06-15T23:59:00Z",
      "scanned_by": null,
      "scan_location": "Home Office Casework Hub - Sheffield"
    },
    {
      "document_id": "ho-doc-003-0000494",
      "type": "BANK_STATEMENT",
      "filename": "BANK_STATEMENT_002.pdf",
      "signed_url": "https://gov-doc-store.homeoffice.gov.uk/applications/HO-ST-2026-0000494/BANK_STATEMENT/BANK_STATEMENT_002.pdf?sig=HMAC_GOV_SIGNATURE_REDACTED&exp=2026-07-15T23:59:59Z",
      "mime_type": "application/pdf",
      "size_bytes": 2779,
      "uploaded_at": "2026-06-16T00:02:00Z",
      "scanned_by": null,
      "scan_location": "Home Office Casework Hub - Croydon"
    },
    {
      "document_id": "ho-doc-004-0000494",
      "type": "BANK_STATEMENT",
      "filename": "BANK_STATEMENT_003.pdf",
      "signed_url": "https://gov-doc-store.homeoffice.gov.uk/applications/HO-ST-2026-0000494/BANK_STATEMENT/BANK_STATEMENT_003.pdf?sig=HMAC_GOV_SIGNATURE_REDACTED&exp=2026-07-15T23:59:59Z",
      "mime_type": "application/pdf",
      "size_bytes": 2788,
      "uploaded_at": "2026-06-16T00:05:00Z",
      "scanned_by": null,
      "scan_location": "Home Office Casework Hub - Liverpool"
    },
    {
      "document_id": "ho-doc-005-0000494",
      "type": "ACADEMIC_TRANSCRIPT",
      "filename": "ACADEMIC_TRANSCRIPT_001.pdf",
      "signed_url": "https://gov-doc-store.homeoffice.gov.uk/applications/HO-ST-2026-0000494/ACADEMIC_TRANSCRIPT/ACADEMIC_TRANSCRIPT_001.pdf?sig=HMAC_GOV_SIGNATURE_REDACTED&exp=2026-07-15T23:59:59Z",
      "mime_type": "application/pdf",
      "size_bytes": 1982,
      "uploaded_at": "2026-06-16T00:08:00Z",
      "scanned_by": null,
      "scan_location": "Home Office Casework Hub - Glasgow"
    },
    {
      "document_id": "ho-doc-006-0000494",
      "type": "IELTS_CERTIFICATE",
      "filename": "IELTS_CERTIFICATE_001.pdf",
      "signed_url": "https://gov-doc-store.homeoffice.gov.uk/applications/HO-ST-2026-0000494/IELTS_CERTIFICATE/IELTS_CERTIFICATE_001.pdf?sig=HMAC_GOV_SIGNATURE_REDACTED&exp=2026-07-15T23:59:59Z",
      "mime_type": "application/pdf",
      "size_bytes": 2052,
      "uploaded_at": "2026-06-16T00:11:00Z",
      "scanned_by": null,
      "scan_location": "Home Office Casework Hub - Glasgow"
    },
    {
      "document_id": "ho-doc-007-0000494",
      "type": "TB_CERTIFICATE",
      "filename": "TB_CERTIFICATE_001.pdf",
      "signed_url": "https://gov-doc-store.homeoffice.gov.uk/applications/HO-ST-2026-0000494/TB_CERTIFICATE/TB_CERTIFICATE_001.pdf?sig=HMAC_GOV_SIGNATURE_REDACTED&exp=2026-07-15T23:59:59Z",
      "mime_type": "application/pdf",
      "size_bytes": 2073,
      "uploaded_at": "2026-06-16T00:14:00Z",
      "scanned_by": null,
      "scan_location": "Home Office Casework Hub - Sheffield"
    },
    {
      "document_id": "ho-doc-008-0000494",
      "type": "PHOTO",
      "filename": "PHOTO_001.jpg",
      "signed_url": "https://gov-doc-store.homeoffice.gov.uk/applications/HO-ST-2026-0000494/PHOTO/PHOTO_001.jpg?sig=HMAC_GOV_SIGNATURE_REDACTED&exp=2026-07-15T23:59:59Z",
      "mime_type": "image/jpeg",
      "size_bytes": 17622,
      "uploaded_at": "2026-06-16T00:17:00Z",
      "scanned_by": null,
      "scan_location": "Home Office Casework Hub - Croydon"
    }
  ],
  "callback_url": "https://casework-api.homeoffice.gov.uk/api/v1/dis-decisions/HO-ST-2026-0000494",
  "anomaly_type": "fail_rules",
  "anomaly_details": [
    "maintenance funds below Student route requirement",
    "CAS sponsor record requires verification"
  ],
  "recommendation": "RECOMMEND_REJECT"
}
