{
  "source_application_id": "HO-ST-2026-0000375",
  "source_reference": "GV-DEMO-0000375",
  "source_channel": "govdirect",
  "visa_type": "student",
  "country_code": "GB",
  "submitted_at": "2026-06-12T23:15:00Z",
  "caseworker_id": null,
  "applicant": {
    "email": "folake.adebayo.0255@protonmail.com",
    "first_name": "Folake",
    "middle_name": "Adaeze",
    "last_name": "Adebayo",
    "date_of_birth": "1986-11-28",
    "nationality_code": "NG",
    "gender": "F"
  },
  "passport_data": {
    "number": "A9779486",
    "issuing_country": "NG",
    "nationality": "NG",
    "full_name": "ADEBAYO FOLAKE ADAEZE",
    "date_of_birth": "1986-11-28",
    "gender": "F",
    "issue_date": "2020-01-03",
    "expiry_date": "2030-01-03",
    "mrz_line1": "P<NGAADEBAYO<<FOLAKE<ADAEZE<<<<<<<<<<<<<<<<<",
    "mrz_line2": "A9779486<8NGA8611286F3001031<<<<<<<<<<<<<<04"
  },
  "biometric_verification": {
    "method": "vac_in_person",
    "vac_location": "VAC London - 66 Wilson Street, EC2A 2BT",
    "vac_appointment_date": "2026-06-13",
    "fingerprints_captured": true,
    "photograph_captured": true,
    "identity_verified_by": "HO-BIO-Officer-1255",
    "verified_at": "2026-06-13T11:15:00Z",
    "provider": "home_office_vac",
    "mrz_check_passed": true,
    "face_match_score": null,
    "liveness_passed": null
  },
  "answers": {
    "personalInfo": {
      "firstName": "Folake",
      "middleName": "Adaeze",
      "lastName": "Adebayo",
      "dateOfBirth": "1986-11-28",
      "nationality": "NG",
      "maritalStatus": "married"
    },
    "employment": {
      "status": "student_applicant",
      "employerName": "University of Manchester",
      "sponsorLicenceNumber": "STU-2026-4821",
      "sponsorStatus": "ACTIVE",
      "sponsorRating": "A",
      "jobTitle": "MSc Data Science student",
      "annualIncome": 0.0,
      "monthlyGrossPay": 0.0,
      "cosReferenceNumber": null,
      "cosIssueDate": null,
      "cosExpiryDate": null,
      "socCode": null,
      "socTitle": null,
      "socGoingRateAnnual": null,
      "startDate": "2026-09-22",
      "salaryFrequency": null,
      "hoursPerWeek": null,
      "isNewEntrant": null,
      "newEntrantReason": null,
      "previousUkEmployment": false,
      "casReferenceNumber": "CAS-2026-UM-438921",
      "courseTitle": "MSc Data Science",
      "courseLevel": "RQF Level 7",
      "tuitionFeesGbp": 28600,
      "maintenanceFundsGbp": 12006
    },
    "fees": {
      "ihsReferenceNumber": "IHS-2026-0255-4335",
      "visaFeeReference": "VF-2026-ST-000375",
      "paymentConfirmed": true
    },
    "englishLanguage": {
      "exemptNationality": false,
      "testType": "IELTS_ACADEMIC",
      "testReferenceNumber": "26NG431702ADE",
      "overallScore": 6.5,
      "speakingScore": 6.5,
      "listeningScore": 6.5,
      "readingScore": 7.0,
      "writingScore": 6.5,
      "testDate": "2026-02-18"
    },
    "travelHistory": {
      "previousUkVisas": [],
      "previousUkRefusals": false,
      "previousDeportations": false,
      "countriesVisitedLast5Years": [
        "NG",
        "GB"
      ]
    },
    "criminalRecord": {
      "hasConvictions": false,
      "hasPendingCharges": false,
      "hasCivilJudgments": false
    },
    "healthDeclaration": {
      "hasTbCertificate": true,
      "hasHealthConditions": false,
      "requiresAccessibility": false,
      "tbCertificateClinicName": "IOM Migration Health Assessment Centre, Nigeria",
      "tbCertificateClinicCountry": "NG"
    },
    "routeSpecific": {
      "route": "student",
      "phase": "PHASE_2_QUEUE_ONLY",
      "phase_note": "DIS pipeline configured - full deep review live in Phase 2.",
      "display_label": "Student"
    }
  },
  "documents": [
    {
      "document_id": "ho-doc-001-0000375",
      "type": "PASSPORT",
      "filename": "PASSPORT_001.pdf",
      "signed_url": "https://gov-doc-store.homeoffice.gov.uk/applications/HO-ST-2026-0000375/PASSPORT/PASSPORT_001.pdf?sig=HMAC_GOV_SIGNATURE_REDACTED&exp=2026-07-15T23:59:59Z",
      "mime_type": "application/pdf",
      "size_bytes": 2458,
      "uploaded_at": "2026-06-12T22:33:00Z",
      "scanned_by": null,
      "scan_location": "Home Office Casework Hub - Glasgow"
    },
    {
      "document_id": "ho-doc-002-0000375",
      "type": "BANK_STATEMENT",
      "filename": "BANK_STATEMENT_001.pdf",
      "signed_url": "https://gov-doc-store.homeoffice.gov.uk/applications/HO-ST-2026-0000375/BANK_STATEMENT/BANK_STATEMENT_001.pdf?sig=HMAC_GOV_SIGNATURE_REDACTED&exp=2026-07-15T23:59:59Z",
      "mime_type": "application/pdf",
      "size_bytes": 2784,
      "uploaded_at": "2026-06-12T22:36:00Z",
      "scanned_by": null,
      "scan_location": "Home Office Casework Hub - Croydon"
    },
    {
      "document_id": "ho-doc-003-0000375",
      "type": "BANK_STATEMENT",
      "filename": "BANK_STATEMENT_002.pdf",
      "signed_url": "https://gov-doc-store.homeoffice.gov.uk/applications/HO-ST-2026-0000375/BANK_STATEMENT/BANK_STATEMENT_002.pdf?sig=HMAC_GOV_SIGNATURE_REDACTED&exp=2026-07-15T23:59:59Z",
      "mime_type": "application/pdf",
      "size_bytes": 2779,
      "uploaded_at": "2026-06-12T22:39:00Z",
      "scanned_by": null,
      "scan_location": "Home Office Casework Hub - Liverpool"
    },
    {
      "document_id": "ho-doc-004-0000375",
      "type": "BANK_STATEMENT",
      "filename": "BANK_STATEMENT_003.pdf",
      "signed_url": "https://gov-doc-store.homeoffice.gov.uk/applications/HO-ST-2026-0000375/BANK_STATEMENT/BANK_STATEMENT_003.pdf?sig=HMAC_GOV_SIGNATURE_REDACTED&exp=2026-07-15T23:59:59Z",
      "mime_type": "application/pdf",
      "size_bytes": 2791,
      "uploaded_at": "2026-06-12T22:42:00Z",
      "scanned_by": null,
      "scan_location": "Home Office Casework Hub - Glasgow"
    },
    {
      "document_id": "ho-doc-005-0000375",
      "type": "ACADEMIC_TRANSCRIPT",
      "filename": "ACADEMIC_TRANSCRIPT_001.pdf",
      "signed_url": "https://gov-doc-store.homeoffice.gov.uk/applications/HO-ST-2026-0000375/ACADEMIC_TRANSCRIPT/ACADEMIC_TRANSCRIPT_001.pdf?sig=HMAC_GOV_SIGNATURE_REDACTED&exp=2026-07-15T23:59:59Z",
      "mime_type": "application/pdf",
      "size_bytes": 1974,
      "uploaded_at": "2026-06-12T22:45:00Z",
      "scanned_by": null,
      "scan_location": "Home Office Casework Hub - Sheffield"
    },
    {
      "document_id": "ho-doc-006-0000375",
      "type": "IELTS_CERTIFICATE",
      "filename": "IELTS_CERTIFICATE_001.pdf",
      "signed_url": "https://gov-doc-store.homeoffice.gov.uk/applications/HO-ST-2026-0000375/IELTS_CERTIFICATE/IELTS_CERTIFICATE_001.pdf?sig=HMAC_GOV_SIGNATURE_REDACTED&exp=2026-07-15T23:59:59Z",
      "mime_type": "application/pdf",
      "size_bytes": 2056,
      "uploaded_at": "2026-06-12T22:48:00Z",
      "scanned_by": null,
      "scan_location": "Home Office Casework Hub - Sheffield"
    },
    {
      "document_id": "ho-doc-007-0000375",
      "type": "TB_CERTIFICATE",
      "filename": "TB_CERTIFICATE_001.pdf",
      "signed_url": "https://gov-doc-store.homeoffice.gov.uk/applications/HO-ST-2026-0000375/TB_CERTIFICATE/TB_CERTIFICATE_001.pdf?sig=HMAC_GOV_SIGNATURE_REDACTED&exp=2026-07-15T23:59:59Z",
      "mime_type": "application/pdf",
      "size_bytes": 2078,
      "uploaded_at": "2026-06-12T22:51:00Z",
      "scanned_by": null,
      "scan_location": "Home Office Casework Hub - Croydon"
    },
    {
      "document_id": "ho-doc-008-0000375",
      "type": "PHOTO",
      "filename": "PHOTO_001.jpg",
      "signed_url": "https://gov-doc-store.homeoffice.gov.uk/applications/HO-ST-2026-0000375/PHOTO/PHOTO_001.jpg?sig=HMAC_GOV_SIGNATURE_REDACTED&exp=2026-07-15T23:59:59Z",
      "mime_type": "image/jpeg",
      "size_bytes": 17622,
      "uploaded_at": "2026-06-12T22:54:00Z",
      "scanned_by": null,
      "scan_location": "Home Office Casework Hub - Liverpool"
    }
  ],
  "callback_url": "https://casework-api.homeoffice.gov.uk/api/v1/dis-decisions/HO-ST-2026-0000375",
  "anomaly_type": "clean",
  "anomaly_details": null,
  "recommendation": "RECOMMEND_APPROVE"
}
